{
  "project_info": {
    "project_number": "886504217577",
    "project_id": "inventory-management-b610f",
    "storage_bucket": "inventory-management-b610f.firebasestorage.app"
  },
  "client": [
    {
      "client_info": {
        "mobilesdk_app_id": "1:886504217577:android:95d1807219afa316178978",
        "android_client_info": {
          "package_name": "com.example.inventorymanagement"
        }
      },
      "oauth_client": [],
      "api_key": [
        {
          "current_key": "AIzaSyBpy6J-S5Quahd4zVxbL5K3bochd4XEnxw"
        }
      ],
      "services": {
        "appinvite_service": {
          "other_platform_oauth_client": []
        }
      }
    }
  ],
  "configuration_version": "1"
}